{
    "name": "rjy",
    "email": "saikirangadhamsetti@gmail.com",
    "phone": "+16309609226",
    "education": [],
    "work_experience": [
        {
            "company_name": "Technology used: Python,Flask,VS buildtools , MySql.",
            "job_title": "Responsibilities:",
            "dates_worked": "",
            "additional_info": [
                "To design and provide a good user interface which involves processing the videos so as to give the",
                "user the top 10 videos in his selected choice using collaborative filtering approach which was",
                "implemented using ANN algorithm.And worked on creating database for the same.",
                "Co-curricular Activities:-",
                "\uf0b7 Successfully completed the \u201cC programming\u201d test organized at Santhiram Engineering",
                "college,nandyal.",
                "\uf0b7 Successfully completed and Achieved a certificate from \u201cHACKERRANK\u201d in \u201cPYTHON",
                "PROGRAMMING\u201d.",
                "\uf0b7 Successfully completed and Achieved a certificate from \u201cUDEMY\u201d in \u201cDJANGO\u201d.",
                "\uf0b7 Successfully completed and Achieved a certificate from \u201cCOURSERA\u201din \u201cDATABASE",
                "MANAGEMENT ESSENTIALS\u201d.",
                "Hobbies and Interest:-",
                "\uf0b7 Dancing and Fitness.",
                "STRENGTHS:-",
                "\uf0b7 Creativity and Adaptibility",
                "\uf0b7 Quick learning to new things and independent learner",
                "\uf0b7 Critical Thinking and Problem Solving skills",
                "Declaration:-",
                "I hereby declare that the details and information given above are complete and true to the best of my",
                "knowledge.",
                "",
                "",
                "Date:27/05/2023",
                "(G.Sai Kiran)"
            ]
        }
    ],
    "linkedin": "",
    "github": ""
}