{
    "name": "Graphic Designer",
    "email": "Knithy21@gmail.com",
    "phone": "+918217731735",
    "skills": [
        "and To Apply Them Practically For The Overall",
        "Development Of  The Concern I work For And Myself.",
        "Kiruba NIthy",
        "Graphic Designer & VFX Artist"
    ],
    "education": [
        {
            "university_name": "B.SC VISUAL COMMUNICATION",
            "course_name": "MANONMANIAM SUNDARANAR UNIVERSITY",
            "dates_attended": "2010-2013",
            "marks_or_percentage": "",
            "additional_info": ""
        },
        {
            "university_name": "Aggregate of  65.8% .",
            "course_name": "2010",
            "dates_attended": "2013",
            "marks_or_percentage": "",
            "additional_info": ""
        },
        {
            "university_name": "PROFILE",
            "course_name": "Dedicated & Hard working Graphic Designer & VFX With 10 Years Experince",
            "dates_attended": "10 Years Experince",
            "marks_or_percentage": "",
            "additional_info": ""
        },
        {
            "university_name": "Who Loves To Pursue a Challenging Career That Provides Me Opportunities",
            "course_name": "To Widen My Skills and To Apply Them Practically For The Overall",
            "dates_attended": "",
            "marks_or_percentage": "",
            "additional_info": ""
        },
        {
            "university_name": "Development Of  The Concern I work For And Myself.",
            "course_name": "Kiruba NIthy",
            "dates_attended": "",
            "marks_or_percentage": "",
            "additional_info": ""
        },
        {
            "university_name": "Graphic Designer & VFX Artist",
            "course_name": "",
            "dates_attended": "",
            "marks_or_percentage": "",
            "additional_info": ""
        }
    ],
    "work_experience": [],
    "linkedin": "",
    "github": ""
}